RvLProMaster/__init__.py
RvLProMaster/bot/__init__.py
RvLProMaster/bot/bot.py
RvLProMaster/bot/bot_command.py
RvLProMaster/bot/callback_handler.py
RvLProMaster/bot/events.py
RvLProMaster/bot/parse_mode.py
RvLProMaster/bot/Methods/__init__.py
RvLProMaster/bot/Methods/answerCallbackQuery.py
RvLProMaster/bot/Methods/approveChatJoinRequest.py
RvLProMaster/bot/Methods/banChatMember.py
RvLProMaster/bot/Methods/banChatSenderChat.py
RvLProMaster/bot/Methods/close.py
RvLProMaster/bot/Methods/closeForumTopic.py
RvLProMaster/bot/Methods/closeGeneralForumTopic.py
RvLProMaster/bot/Methods/copyMessage.py
RvLProMaster/bot/Methods/createChatInviteLink.py
RvLProMaster/bot/Methods/createForumTopic.py
RvLProMaster/bot/Methods/declineChatJoinRequest.py
RvLProMaster/bot/Methods/deleteChatStickerSet.py
RvLProMaster/bot/Methods/deleteForumTopic.py
RvLProMaster/bot/Methods/deleteMessage.py
RvLProMaster/bot/Methods/editChatInviteLink.py
RvLProMaster/bot/Methods/editForumTopic.py
RvLProMaster/bot/Methods/editGeneralForumTopic.py
RvLProMaster/bot/Methods/editMessageCaption.py
RvLProMaster/bot/Methods/editMessageLiveLocation.py
RvLProMaster/bot/Methods/editMessageMedia.py
RvLProMaster/bot/Methods/editMessageReplyMarkup.py
RvLProMaster/bot/Methods/editMessageText.py
RvLProMaster/bot/Methods/exportChatInviteLink.py
RvLProMaster/bot/Methods/forwardMessage.py
RvLProMaster/bot/Methods/getAvailableGifts.py
RvLProMaster/bot/Methods/getChat.py
RvLProMaster/bot/Methods/getChatAdministrators.py
RvLProMaster/bot/Methods/getChatMember.py
RvLProMaster/bot/Methods/getChatMemberCount.py
RvLProMaster/bot/Methods/getFile.py
RvLProMaster/bot/Methods/getForumTopicIconStickers.py
RvLProMaster/bot/Methods/getMe.py
RvLProMaster/bot/Methods/getMyDescription.py
RvLProMaster/bot/Methods/getMyName.py
RvLProMaster/bot/Methods/getMyShortDescription.py
RvLProMaster/bot/Methods/getUserChatBoosts.py
RvLProMaster/bot/Methods/getUserProfilePhotos.py
RvLProMaster/bot/Methods/hideGeneralForumTopic.py
rvlpromaster-0.1.6.dist-info/licenses/LICENSE
rvlpromaster-0.1.6.dist-info/METADATA
rvlpromaster-0.1.6.dist-info/WHEEL
rvlpromaster-0.1.6.dist-info/top_level.txt
rvlpromaster-0.1.6.dist-info/RECORD
