Metadata-Version: 2.4
Name: RvLProMaster
Version: 0.1.6
Summary: A Telegram Bot API for Python
Author-email: Yudho Patrianto <kydh01123@gmail.com>
License: MIT
Project-URL: Homepage, https://github.com/YudhoPRJKT-Teams/RvLProMaster
Project-URL: Source, https://github.com/YudhoPRJKT-Teams/RvLProMaster
Project-URL: Issues, https://github.com/YudhoPRJKT-Teams/RvLProMaster/issues
Requires-Python: >=3.11
License-File: LICENSE
Requires-Dist: aiohttp[speedups]
Requires-Dist: python-dotenv
Requires-Dist: telegraph
Requires-Dist: openai
Requires-Dist: google-genai
Requires-Dist: markdown
Requires-Dist: yt-dlp
Requires-Dist: Pillow
Dynamic: license-file
